odoo/addons/l10n_th_account_wht_cert_form/README.rst
odoo/addons/l10n_th_account_wht_cert_form/__init__.py
odoo/addons/l10n_th_account_wht_cert_form/__manifest__.py
odoo/addons/l10n_th_account_wht_cert_form/data/mail_template.xml
odoo/addons/l10n_th_account_wht_cert_form/data/paper_format.xml
odoo/addons/l10n_th_account_wht_cert_form/data/withholding_tax_cert_data.xml
odoo/addons/l10n_th_account_wht_cert_form/i18n/l10n_th_account_wht_cert_form.pot
odoo/addons/l10n_th_account_wht_cert_form/models/__init__.py
odoo/addons/l10n_th_account_wht_cert_form/models/res_company.py
odoo/addons/l10n_th_account_wht_cert_form/models/res_config_settings.py
odoo/addons/l10n_th_account_wht_cert_form/models/withholding_tax_cert.py
odoo/addons/l10n_th_account_wht_cert_form/readme/CONTRIBUTORS.rst
odoo/addons/l10n_th_account_wht_cert_form/readme/DESCRIPTION.rst
odoo/addons/l10n_th_account_wht_cert_form/readme/USAGE.rst
odoo/addons/l10n_th_account_wht_cert_form/reports/withholding_tax_cert_form_view.xml
odoo/addons/l10n_th_account_wht_cert_form/static/description/icon.png
odoo/addons/l10n_th_account_wht_cert_form/static/description/index.html
odoo/addons/l10n_th_account_wht_cert_form/static/src/img/WithholdingCert.png
odoo/addons/l10n_th_account_wht_cert_form/static/src/scss/style_report.scss
odoo/addons/l10n_th_account_wht_cert_form/tests/__init__.py
odoo/addons/l10n_th_account_wht_cert_form/tests/test_wht_cert_form.py
odoo/addons/l10n_th_account_wht_cert_form/views/res_config_settings_views.xml
odoo_addon_l10n_th_account_wht_cert_form-16.0.1.2.0.dist-info/METADATA
odoo_addon_l10n_th_account_wht_cert_form-16.0.1.2.0.dist-info/WHEEL
odoo_addon_l10n_th_account_wht_cert_form-16.0.1.2.0.dist-info/top_level.txt
odoo_addon_l10n_th_account_wht_cert_form-16.0.1.2.0.dist-info/RECORD
